{
"parallel": 1,
"n_polygons": 87198244,
"n_frontier_edges": 0,
"n_barrier_edge_tips": 0,
"n_half_edges": 523226816,
"n_faces": 174396488,
"n_vertices": 87216921,
"n_polygons_to_repair": 0,
"n_polygons_added_after_repair": 0,
"time_triangulation_generation": 310380,
"d_time_copy_to_device": 590.987,
"d_time_to_label_max_edges": 28.1166,
"d_time_to_label_frontier_edges": 21.2224,
"d_time_to_label_seed_edges": 21.3749,
"d_time_to_label_extra_frontier_edge": 26.8405,
"d_time_to_label_scan_edges": 8.44349,
"d_time_to_label_compaction_edges": 4.79316,
"d_time_to_label_total": 70.714,
"d_time_to_traversal_and_repair": 0,
"d_time_to_traversal": 33.1566,
"d_time_to_traversal_search_frontier_edge": 13.8058,
"d_time_to_back_to_host": 827.577,
"d_time_to_overwrite_seed": 15.7842,
"d_time_to_generate_polygonal_mesh": 70.714,
	"memory_max_edges": 2092907264,
	"memory_frontier_edge": 2092907264,
	"memory_seed_edges": 4185814528,
	"memory_seed_bet_mar": 1046453632,
	"memory_triangle_list": 697585952,
	"memory_mesh_input": 10466030520,
	"memory_mesh_output": 10464536320,
	"memory_vertices_input": 2093206104,
	"memory_vertices_output": 2093206104,
	"memory_total": 35232647688,
	"memory_total_gpu": 34006106112
}
