{
"parallel": 1,
"n_polygons": 36120100,
"n_frontier_edges": 0,
"n_barrier_edge_tips": 0,
"n_half_edges": 216744640,
"n_faces": 72240200,
"n_vertices": 36132121,
"n_polygons_to_repair": 0,
"n_polygons_added_after_repair": 0,
"time_triangulation_generation": 112448,
"d_time_copy_to_device": 248.085,
"d_time_to_label_max_edges": 11.8831,
"d_time_to_label_frontier_edges": 8.67732,
"d_time_to_label_seed_edges": 8.77336,
"d_time_to_label_extra_frontier_edge": 11.2381,
"d_time_to_label_scan_edges": 3.59512,
"d_time_to_label_compaction_edges": 2.02763,
"d_time_to_label_total": 29.3338,
"d_time_to_traversal_and_repair": 0,
"d_time_to_traversal": 13.7552,
"d_time_to_traversal_search_frontier_edge": 5.76168,
"d_time_to_back_to_host": 341.429,
"d_time_to_overwrite_seed": 6.54666,
"d_time_to_generate_polygonal_mesh": 29.3338,
	"memory_max_edges": 866978560,
	"memory_frontier_edge": 866978560,
	"memory_seed_edges": 1733957120,
	"memory_seed_bet_mar": 433489280,
	"memory_triangle_list": 288960800,
	"memory_mesh_input": 4335854520,
	"memory_mesh_output": 4334892800,
	"memory_vertices_input": 867170904,
	"memory_vertices_output": 867170904,
	"memory_total": 14595453448,
	"memory_total_gpu": 14395572224
}
