{
"parallel": 1,
"n_polygons": 10547470,
"n_frontier_edges": 0,
"n_barrier_edge_tips": 0,
"n_half_edges": 208997550,
"n_faces": 69660901,
"n_vertices": 34837875,
"n_polygons_to_repair": 0,
"n_polygons_added_after_repair": 0,
"time_triangulation_generation": 242312,
"d_time_copy_to_device": 395.232,
"d_time_to_label_max_edges": 10.15,
"d_time_to_label_frontier_edges": 4.3726,
"d_time_to_label_seed_edges": 4.34909,
"d_time_to_label_scan_edges": 2.52487,
"d_time_to_label_compaction_edges": 1.36057,
"d_time_to_label_total": 18.8717,
"d_time_to_traversal_and_repair": 0,
"d_time_to_traversal": 15.0743,
"d_time_to_traversal_search_frontier_edge": 2.64367,
"d_time_to_back_to_host": 414.138,
"d_time_to_repair": 0,
"d_time_to_generate_polygonal_mesh": 18.8717,
	"memory_max_edges": 835990200,
	"memory_frontier_edge": 835990200,
	"memory_seed_edges": 1671980400,
	"memory_seed_bet_mar": 417995100,
	"memory_triangle_list": 278643604,
	"memory_mesh_input": 5368709120,
	"memory_mesh_output": 4179951000,
	"memory_vertices_input": 836109000,
	"memory_vertices_output": 836109000,
	"memory_total": 15261477624,
	"memory_total_gpu": 13926072320
}
