{
"n_polygons": 2067637,
"n_frontier_edges": 8482485,
"n_barrier_edge_tips": 127526,
"n_half_edges": 38471800,
"n_faces": 12821841,
"n_vertices": 6414060,
"n_polygons_to_repair": 113129,
"n_polygons_added_after_repair": 239866,
"time_triangulation_generation": 32422.3,
"time_to_label_max_edges": 6113.69,
"time_to_label_frontier_edges": 1619.22,
"time_to_label_seed_edges": 2093.88,
"time_to_label_total": 9826.78,
"time_to_traversal_and_repair": 2583.36,
"time_to_traversal": 2273.89,
"time_to_repair": 309.463,
"time_to_generate_polygonal_mesh": 12410.1,
	"memory_max_edges": 38471800,
	"memory_frontier_edge": 38471800,
	"memory_seed_edges": 8388608,
	"memory_seed_bet_mar": 38471800,
	"memory_triangle_list": 64,
	"memory_mesh_input": 769687200,
	"memory_mesh_output": 769436000,
	"memory_vertices_input": 153937440,
	"memory_vertices_output": 153937440,
	"memory_total": 1970802152
}
