{
"n_polygons": 22648081,
"n_frontier_edges": 45305680,
"n_barrier_edge_tips": 0,
"n_half_edges": 135907522,
"n_faces": 45296162,
"n_vertices": 22657600,
"n_polygons_to_repair": 0,
"n_polygons_added_after_repair": 0,
"time_triangulation_generation": 75479.3,
"time_to_label_max_edges": 15131.9,
"time_to_label_frontier_edges": 4134.94,
"time_to_label_seed_edges": 6280.65,
"time_to_label_total": 25547.5,
"time_to_traversal_and_repair": 6695.91,
"time_to_traversal": 6695.91,
"time_to_repair": 0,
"time_to_generate_polygonal_mesh": 32243.4,
	"memory_max_edges": 135907522,
	"memory_frontier_edge": 135907522,
	"memory_seed_edges": 134217728,
	"memory_seed_bet_mar": 135907522,
	"memory_triangle_list": 0,
	"memory_mesh_input": 2718912000,
	"memory_mesh_output": 2718150440,
	"memory_vertices_input": 543782400,
	"memory_vertices_output": 543782400,
	"memory_total": 7066567534
}
